{
    "name": "[嘎嘎小羊莓] 嘎嘎青花",
    "blur_strength": 4,
    "main_text_color": "rgba(3, 17, 22, 1)",
    "italics_text_color": "rgba(183, 28, 7, 1)",
    "underline_text_color": "rgba(189, 181, 11, 1)",
    "quote_text_color": "rgba(50, 122, 162, 0.84)",
    "blur_tint_color": "rgba(250, 245, 235, 1)",
    "chat_tint_color": "rgba(250, 245, 235, 1)",
    "user_mes_blur_tint_color": "rgba(245, 250, 255, 0.9)",
    "bot_mes_blur_tint_color": "rgba(240, 250, 255, 1)",
    "shadow_color": "rgba(28, 69, 87, 0.62)",
    "shadow_width": 0,
    "border_color": "rgba(150, 180, 200, 1)",
    "font_scale": 1.1,
    "fast_ui_mode": false,
    "waifuMode": false,
    "avatar_style": 2,
    "chat_display": 0,
    "noShadows": false,
    "chat_width": 55,
    "timer_enabled": true,
    "timestamps_enabled": false,
    "timestamp_model_icon": false,
    "mesIDDisplay_enabled": true,
    "hideChatAvatars_enabled": false,
    "message_token_count_enabled": true,
    "expand_message_actions": false,
    "enableZenSliders": true,
    "enableLabMode": false,
    "hotswap_enabled": true,
    "custom_css": "/*==================== 主题：小狗嘎嘎青花 ====================*/    \n/* 主色：#FAF5EB 米白 | 强调 #0A2D3C | 字体 #222 */\nq {\n  text-decoration: underline dashed 2.5px #88A3BC;\n  text-underline-offset: 4px;\n  font-style: normal;\n  color: #38506B;\n  padding: 1px 6px;\n  border-radius: 5px;\n}\n\n.regex-script-label {    \n    max-width: 94%;    \n}    \n.mes_block {    \n  margin-bottom: 45px !important;    \n}    \n@media screen and (max-width: 720px) {    \n  :root {    \n    --mes-width: 100vw;    \n    --mes-block-width: 100vw;    \n  }    \n  .mes, .mes_block {    \n    width: 100vw !important;    \n    max-width: 99vw !important;    \n    margin-left: 0 !important;    \n    margin-right: 0 !important;    \n    box-sizing: border-box !important;    \n  }    \n  .mes_block {    \n    padding: 0 !important;    \n  }    \n}    \n.mesAvatarWrapper .avatar img {    \n  width: 56px;    \n  height: 56px;    \n  object-fit: cover;    \n  border-radius: 50%;    \n  border: 1.5px solid #0A2D3C;      /* 深蓝描边 */    \n  box-shadow: none;    \n  filter: none;    \n}    \n/* 底栏QR按键隐藏 */    \n#send_form:hover #qr--bar {    \n    height: 40px;    \n    transition: all 0.5s ease;    \n}    \n#qr--bar {    \n    height: 0.1px;    \n}    \ncode span.comment {    \n    color: #90877A;    \n    font-style: italic;    \n}    \nbody {    \n    font-family: 'ZhuqueFangsong', serif;    \n    line-height: 1.5;    \n    font-weight: 300;    \n    background: #FAF5EB;                /* 米白背景 */    \n    color: #222;                        /* 深灰文字 */    \n}    \n@font-face {    \n    font-family: 'ZhuqueFangsong';    \n    src: url(\"http://sharkpan.xyz/f/24j6iQ/%E4%B8%AD%E6%96%87%20-%20Huiwen.otf\") format('truetype');    \n    font-weight: 200;    \n    font-style: normal;    \n}    \n@font-face {    \n  font-family: 'Huiwen';    \n  src: url(\"http://sharkpan.xyz/f/24j6iQ/%E4%B8%AD%E6%96%87%20-%20Huiwen.otf\") format('opentype');    \n  font-weight: 400;    \n  font-style: normal;    \n}    \n\n/* 强制输入框使用该字体 */    \ntextarea, input[type=\"text\"] {    \n  font-family: 'Huiwen', 'ZhuqueFangsong', serif !important;    \n  font-size: 16px;    \n  font-weight: 400;    \n  line-height: 1.6;    \n  color: #0A2D3C; /* 深蓝主色文字 */    \n  background-color: #F3ECE1;    \n  border: 1px solid #0A2D3C;    \n  border-radius: 5px;    \n  padding: 10px;    \n  box-shadow: 3px 3px 5px rgba(10,45,60, 0.08);    \n  outline: none;    \n  transition: all 0.3s ease;    \n}    \n\n*{    \n  --black30a: rgb(10 45 60 / 30%);    \n  --black50a: rgb(10 45 60 / 50%);    \n  --black70a: rgb(10 45 60 / %);    \n  --white20a: rgb(250 245 235 / 20%);    \n  --white30a: rgb(250 245 235 / 30%);    \n  --white50a: rgb(250 245 235 / 50%);    \n  --grey30: rgb(243 236 225);    \n  --grey30a: rgb(243 236 225 / 30%);    \n  --grey7070a: rgb(243 236 225 / 70%);    \n}    \n/* 聊天消息容器整体居中布局 */    \n.mes {    \n  display: flex;    \n  flex-direction: column;    \n  align-items: center;    \n  margin: 10px 0 20px 0;    \n}    \n/* 头像容器：整体下移（关键） */    \n.mesAvatarWrapper {    \n  display: flex;    \n  flex-direction: column;    \n  align-items: center;    \n  justify-content: center;    \n  margin-top: 100px;    \n  margin-bottom: 10px;    \n}    \n/* 信息类（楼层、计时、token）设置为 inline，颜色继承 */    \n.mesIDDisplay,    \n.mes_timer,    \n.tokenCounterDisplay {    \n  display: inline-block;    \n  color: #5C6973; /* 深蓝灰 */    \n  font-size: 12px;    \n  opacity: 0.85;    \n  margin: 2px 4px;    \n  font-family: 'ZhuqueFangsong', serif;    \n}    \n/* 信息条（放在头像上或下都行） */    \n.mes_info_bar {    \n  display: flex;    \n  justify-content: center;    \n  align-items: center;    \n  gap: 8px;    \n  font-size: 12px;    \n  color: #5C6973;    \n  font-family: 'ZhuqueFangsong', serif;    \n  opacity: 0.85;    \n  margin-bottom: 6px;    \n}    \n/* 移动端保持一致布局 */    \n@media screen and (max-width: 768px) {    \n  .mesAvatarWrapper {    \n    margin-top: 0px;    \n    margin-bottom: 8px;    \n    width: auto;    \n  }    \n  .mes_block {    \n    max-width: 95%;    \n  }    \n}    \n:root {    \n  --text-token-layout: contents;    \n}    \n.mesIDDisplay,    \n.mes_timer,    \n.tokenCounterDisplay {    \n  display: var(--text-token-layout);    \n  color: #5C6973;    \n}    \n/* 消息整体间距压缩 */    \n.mes {    \n  margin-bottom: 6px;    \n}    \n/* 消息文本紧凑 */    \n.mes_text {    \n  margin: 0;    \n  padding: 0;    \n  line-height: 1.5;    \n}    \n/* 思维链容器 */    \n.mes_reasoning {    \n  border-left: 3px solid #0A2D3C;    \n  padding: 10px;    \n  font-family: 'ZhuqueFangsong', serif;    \n}    \n\n/* 正则脚本标签：黑蓝高质感风格 */    \n.regex-script-label {    \n  font-family: 'Fira Mono', 'Menlo', 'monospace';    \n  background: linear-gradient(102deg, #28425B 80%, #0A2D3C 100%);    \n  color: #FAF5EB;    \n  padding: 5px 12px 5px 12px;    \n  border-radius: 6px;    \n  border: 1.2px solid #0A2D3C;    \n  box-shadow: 0 2px 8px rgba(10,45,60,0.10) inset, 0 1px 1.5px rgba(250,245,235,0.09);    \n  letter-spacing: 0.04em;    \n  font-size: 13px;    \n  font-weight: 500;    \n  margin: 2px 0;    \n  transition: box-shadow 0.18s, border 0.18s;    \n}    \n.regex-script-label:hover {    \n  border-color: #FAF5EB;    \n  box-shadow: 0 4px 18px rgba(10,45,60,0.18) inset, 0 2px 8px rgba(250,245,235,0.10);    \n  color: #0A2D3C;    \n  background: linear-gradient(102deg, #FAF5EB 80%, #E1D5C9 100%);    \n  cursor: pointer;    \n}    \n\n/* 输入框 */    \n.text_pole {    \n  background-color: #F3ECE1;    \n  border: 1px solid #0A2D3C;    \n  border-radius: 6px;    \n  padding: 8px 12px;    \n  font-family: 'ZhuqueFangsong', serif;    \n  color: #0A2D3C;\n}    \n.drawer-icon {    \n  width: 28px;    \n  height: 28px;    \n  font-size: 24px;    \n  line-height: 28px;    \n  color: #0A2D3C;         /* 深蓝主色图标 */    \n  background: none !important;    \n  text-shadow: none !important;    \n  -webkit-background-clip: unset;    \n  -webkit-text-fill-color: unset;    \n  display: inline-flex;    \n  justify-content: center;    \n  align-items: center;    \n  padding: 0;    \n  margin: 6px 6px 3px 3px;    \n  border-radius: 6px;    \n  user-select: none;    \n  flex-shrink: 0;    \n  transition: background-color 0.2s ease;    \n}    \n\nnav, .nav-bar, .drawer, .top-nav, .header-bar {    \n  background-color: #F3ECE1;  /* 米白卡片背景 */    \n  box-shadow: none;    \n  border-bottom: 1px solid #0A2D3C;    \n}    \n/* 悬停效果 */    \n.drawer-icon:hover {    \n  background-color: #0A2D3C;    \n  color: #164F68;\n  cursor: pointer;    \n}    \n/* 水平对齐控制 */    \n.drawer-icon.left {    \n  margin-left: 0;    \n  margin-right: auto;    \n}    \n.drawer-icon.right {    \n  margin-left: auto;    \n  margin-right: 0;    \n}    \n/* 垂直对齐控制 */    \n.drawer-icon.top {    \n  align-self: flex-start;    \n}    \n.drawer-icon.bottom {    \n  align-self: flex-end;    \n}    \ncode {    \n  background-color: #F3ECE1;    \n  color: #0A2D3C;    \n  font-family: 'ZhuqueFangsong', serif;    \n  font-size: 14px;    \n  border: 1px solid #0A2D3C;    \n  border-radius: 5px;    \n  padding: 3px 7px;    \n  box-shadow: none;    \n}    \n/* ===== 头像容器（柔白极简风 + 扩大底部内边距） ===== */    \n.mesAvatarWrapper {    \n  display: flex;    \n  flex-direction: row;    \n  align-items: center;    \n  gap: 12px;    \n  padding-top: 10px;    \n  padding-right: 16px;    \n  padding-bottom: 16px;    \n  padding-left: 16px;    \n  width: 100%;    \n  background-color: transparent !important;    \n  border: 1.5px solid #0A2D3C;    \n  border-radius: 8px;    \n  box-shadow: none;    \n  margin: 12px 0;    \n}    \n/* ===== 头像图像（圆形 + 极简描边） ===== */    \n.avatar img {    \n  width: 56px;    \n  height: 56px;    \n  object-fit: cover;    \n  border-radius: 50%;    \n  border: 1.5px solid #0A2D3C;    \n  background: transparent;    \n  box-shadow: none !important;    \n}    \n\n/* 深色思维链头部容器 */    \n.mes_reasoning_header {    \n  background: #0A2D3C;     /* 深蓝主色 */    \n  border: 1.5px solid #0A2D3C;    \n  border-radius: 10px;    \n  padding: 8px 26px;    \n  margin: 14px auto;    \n  color: #FAF5EB;    \n  box-shadow: 0 4px 16px rgba(10,45,60,0.08);    \n  display: flex;    \n  align-items: center;    \n  justify-content: center;    \n  backdrop-filter: blur(7px);    \n  position: relative;    \n  max-width: 92%;    \n  width: fit-content;    \n}    \n\n/* ☀️ emoji作为左右角标 */    \n.mes_reasoning_header_title::before,    \n.mes_reasoning_header_title::after {    \n  content: \"☀️\";    \n  display: inline-block;    \n  margin: 0 5px;    \n  opacity: 0.75;    \n  filter: drop-shadow(0 0 2px rgba(10,45,60, 0.12));    \n}    \n\n/* 标题文字本身 */    \n.mes_reasoning_header_title {    \n  font-size: 13px;    \n  font-weight: bold;    \n  color: #FAF5EB;    \n  padding: 0 14px;    \n  white-space: nowrap;    \n  overflow: visible;    \n  text-overflow: unset;    \n  text-align: center;    \n  letter-spacing: 0.04em;    \n  text-shadow: 0 1px 6px rgba(10,45,60,0.12), 0 0.5px 2px rgba(250,245,235,0.09);    \n}    \n\n/* 箭头样式简化 */    \n.mes_reasoning_arrow {    \n  font-size: 13px;    \n  color: #FAF5EB;    \n  cursor: pointer;    \n  transition: transform 0.3s ease, color 0.3s ease;    \n  margin-left: 10px;    \n  margin-right: 4px;    \n  vertical-align: middle;    \n}    \n.mes_reasoning_arrow:hover {    \n  color: #0A2D3C;    \n  background: #FAF5EB;\n  transform: scale(1.17);    \n}    \n.mes_block .mes_text {    \n  text-align: justify !important;    \n  padding-right: 5px !important;    \n}    \n\npre {    \n  background-color: #F3ECE1;    \n  color: #0A2D3C;    \n  border: 1px solid #0A2D3C;    \n  border-radius: 10px;    \n  padding: 14px 18px;    \n  margin: 16px 0;    \n  font-family: 'ZhuqueFangsong', serif;    \n  font-size: 13px;    \n  line-height: 1.65;    \n  position: relative;    \n  overflow-x: auto;    \n  box-shadow: inset 0 0 6px rgba(10,45,60,0.09), 0 0 10px rgba(10,45,60,0.10);    \n  transition: box-shadow 0.4s ease, transform 0.3s ease;    \n}    \npre:hover {    \n  box-shadow: inset 0 0 8px rgba(10,45,60,0.16), 0 0 14px rgba(10,45,60,0.16);    \n  transform: translateY(-1px);    \n}    \npre code {    \n  background-color: transparent !important;    \n  color: inherit !important;    \n  font-family: 'Courier New', monospace;    \n  font-size: 13px;    \n  line-height: 1.65;    \n  display: block;    \n  white-space: pre-wrap;    \n  word-break: break-word;    \n  padding-left: 14px;    \n  border-left: 2px solid #0A2D3C;    \n  position: relative;    \n  animation: codeFadeIn 0.4s ease;    \n}    \npre::before {    \n  content: \"❈\";    \n  position: absolute;    \n  top: 8px;    \n  left: 12px;    \n  font-size: 14px;    \n  color: rgba(10,45,60,0.14);    \n}    \n@keyframes codeFadeIn {    \n  0% { opacity: 0; transform: translateY(4px); }    \n  100% { opacity: 1; transform: translateY(0); }    \n}    \npre code {    \n  font-family: 'ZhuqueFangsong', serif;    \n  background-color: #F3ECE1;    \n}    \n#options_button,    \n#extensionsMenuButton,    \n#send_but {    \n  font-size: 18px;    \n  background-size: 60% 60%;    \n  background-position: center;    \n  background-repeat: no-repeat;    \n  color: #0A2D3C;  /* 深蓝图标 */    \n}    \n/* ===== 固定间距系统 ===== */    \n.mes {    \n  margin-bottom: 10px !important;    \n}    \n.mesAvatarWrapper {    \n  padding: 12px 15px !important;    \n  margin-bottom: 0 !important;    \n}    \n.mes_block {    \n  margin-top: -1px !important;    \n  padding: 12px 15px !important;    \n}    \n.mes_block {    \n  margin-bottom: 45px !important;    \n}    \n/* 滑块、滚动条等控件适配浅米蓝风格 */    \n::-webkit-scrollbar {    \n  width: 3px;    \n  background: #FAF5EB",
    "bogus_folders": true,
    "zoomed_avatar_magnification": "",
    "reduced_motion": false,
    "compact_input_area": true,
    "show_swipe_num_all_messages": ""
}